tree_sitter/__init__.py
tree_sitter/binding.cp311-win32.pyd
tree_sitter_languages/__init__.py
tree_sitter_languages/core.cp311-win32.pyd
tree_sitter_languages/languages.dll
tree_sitter_builds-2023.3.12.dist-info/LICENSE
tree_sitter_builds-2023.3.12.dist-info/METADATA
tree_sitter_builds-2023.3.12.dist-info/WHEEL
tree_sitter_builds-2023.3.12.dist-info/top_level.txt
tree_sitter_builds-2023.3.12.dist-info/RECORD
