Metadata-Version: 2.1
Name: tree-sitter-builds
Version: 2023.3.12
Summary: Python bindings to the Tree-sitter parsing library
Home-page: https://github.com/Akuli/py-tree-sitter-builds
Author: Akuli
Author-email: akuviljanen17@gmail.com
License: Apache 2.0
Project-URL: Documentation, https://github.com/Akuli/py-tree-sitter-builds
Project-URL: Source, https://github.com/Akuli/py-tree-sitter-builds
Project-URL: Tracker, https://github.com/Akuli/py-tree-sitter-builds/issues
Requires-Python: >=3.6
License-File: LICENSE
